.coveragerc
.gitignore
.readthedocs.yml
.style.yapf
.travis.yml
CHANGELOG.rst
LICENSE
Makefile
README.rst
mktag
setup.cfg
setup.py
tox.ini
aioserf/__init__.py
aioserf/_version.py
aioserf/client.py
aioserf/codec.py
aioserf/connection.py
aioserf/environment_config.py
aioserf/exceptions.py
aioserf/result.py
aioserf/stream.py
aioserf/util.py
aioserf.egg-info/PKG-INFO
aioserf.egg-info/SOURCES.txt
aioserf.egg-info/dependency_links.txt
aioserf.egg-info/requires.txt
aioserf.egg-info/top_level.txt
ci/rtd-requirements.txt
ci/test-requirements.txt
ci/travis.sh
debian/.gitignore
debian/changelog
debian/compat
debian/control
debian/rules
debian/watch
debian/source/format
docs/Makefile
docs/make.bat
docs/source/conf.py
docs/source/history.rst
docs/source/index.rst
docs/source/rationale.rst
docs/source/usage.rst
docs/source/_static/.git_empty
examples/hammer.py
examples/listener.py
tests/__init__.py
tests/test_client.py
tests/test_client_stream.py
tests/test_connection.py
tests/test_environmentconfig.py
tests/test_result.py