Metadata-Version: 1.0
Name: aioserf
Version: 0.3.3.post3
Summary: Python client for the Serf orchestration tool
Home-page: https://github.com/smurfix/aioserf
Author: Matthias Urlichs
Author-email: matthias@urlichs.de
License: MIT
Keywords: Serf,orchestration,service discovery,anyio
Platform: UNKNOWN
